pypidevtools/__init__.py
pypidevtools-0.0.7.dist-info/METADATA
pypidevtools-0.0.7.dist-info/WHEEL
pypidevtools-0.0.7.dist-info/top_level.txt
pypidevtools-0.0.7.dist-info/RECORD
