Metadata-Version: 2.1
Name: pypidevtools
Version: 0.0.7
Summary: Tools for developing PYPI packages for ML tasks.
Author: JohnDev76
Author-email: johndev76@gmail.com
Keywords: pypidevtools
Classifier: Development Status :: 1 - Planning
Classifier: Intended Audience :: Developers
Classifier: Programming Language :: Python :: 3
Classifier: Operating System :: Unix
Classifier: Operating System :: MacOS :: MacOS X
Classifier: Operating System :: Microsoft :: Windows
